opencmiss/__init__.py
opencmiss/utils/__init__.py
opencmiss/utils/image.py
opencmiss/utils/geometry/__init__.py
opencmiss/utils/geometry/plane.py
opencmiss/utils/maths/__init__.py
opencmiss/utils/maths/algorithms.py
opencmiss/utils/maths/vectorops.py
opencmiss/utils/zinc/__init__.py
opencmiss/utils/zinc/field.py
opencmiss/utils/zinc/finiteelement.py
opencmiss/utils/zinc/general.py
opencmiss/utils/zinc/material.py
opencmiss.utils-0.2.0.dist-info/LICENSE
opencmiss.utils-0.2.0.dist-info/METADATA
opencmiss.utils-0.2.0.dist-info/WHEEL
opencmiss.utils-0.2.0.dist-info/top_level.txt
opencmiss.utils-0.2.0.dist-info/RECORD
