Metadata-Version: 2.1
Name: opencmiss.utils
Version: 0.2.0
Summary: OpenCMISS Utilities for Python.
Home-page: https://github.com/OpenCMISS-Bindings/opencmiss.utils
Author: Hugh Sorby
Author-email: h.sorby@auckland.ac.nz
License: Apache Software License
Platform: UNKNOWN
Requires-Dist: opencmiss.zinc
